epicsmacrolib-0.6.1.dist-info/RECORD
epicsmacrolib-0.6.1.dist-info/LICENSE
epicsmacrolib-0.6.1.dist-info/WHEEL
epicsmacrolib-0.6.1.dist-info/entry_points.txt
epicsmacrolib-0.6.1.dist-info/AUTHORS.rst
epicsmacrolib-0.6.1.dist-info/top_level.txt
epicsmacrolib-0.6.1.dist-info/METADATA
epicsmacrolib/_macro.cpython-311-darwin.so
epicsmacrolib/_iocsh_src.cpp
epicsmacrolib/version.py
epicsmacrolib/_macro_src.pyx
epicsmacrolib/_version.py
epicsmacrolib/__init__.py
epicsmacrolib/iocsh.py
epicsmacrolib/_iocsh_src.pyx
epicsmacrolib/_macro_src.cpp
epicsmacrolib/_iocsh.cpython-311-darwin.so
epicsmacrolib/__main__.py
epicsmacrolib/macro.py
epicsmacrolib/bin/__init__.py
epicsmacrolib/bin/main.py
epicsmacrolib/bin/help.py
epicsmacrolib/bin/expand.py
epicsmacrolib/tests/test_iocsh.py
epicsmacrolib/tests/conftest.py
epicsmacrolib/tests/test_macro.py
epicsmacrolib/tests/__init__.py
