Metadata-Version: 2.1
Name: epicsmacrolib
Version: 0.6.1
Summary: epics-base compliant macro tools
Author: SLAC National Accelerator Laboratory
License: Copyright (c) 2023, The Board of Trustees of the Leland Stanford Junior
Classifier: Development Status :: 2 - Pre-Alpha
Classifier: Natural Language :: English
Classifier: Programming Language :: Python :: 3
Requires-Python: >=3.9
License-File: LICENSE
License-File: AUTHORS.rst
Provides-Extra: docs
Requires-Dist: docs-versions-menu ; extra == 'docs'
Requires-Dist: numpydoc ; extra == 'docs'
Requires-Dist: recommonmark ; extra == 'docs'
Requires-Dist: sphinx ; extra == 'docs'
Requires-Dist: sphinx-copybutton ; extra == 'docs'
Requires-Dist: sphinx-rtd-theme ; extra == 'docs'
Requires-Dist: sphinxcontrib-jquery ; extra == 'docs'
Provides-Extra: test
Requires-Dist: pytest ; extra == 'test'
